minijson.cp311-win_amd64.pyd
minijson-3.1.1.dist-info/LICENSE
minijson-3.1.1.dist-info/METADATA
minijson-3.1.1.dist-info/WHEEL
minijson-3.1.1.dist-info/top_level.txt
minijson-3.1.1.dist-info/RECORD
