Metadata-Version: 2.1
Name: minijson
Version: 3.1.1
Summary: A library for serializing JSON in a small binary format
Home-page: https://git.dms-serwis.com.pl/smokserwis/minijson
Author: Piotr Maślanka
Author-email: pmaslanka@smok.co
License: UNKNOWN
Project-URL: Documentation, https://smokserwis.docs.smok.co/minijson
Project-URL: Code, https://git.dms-serwis.com.pl/smokserwis/minijson
Project-URL: Issue tracker, https://git.dms-serwis.com.pl/smokserwis/minijson/-/issues
Platform: UNKNOWN
Classifier: Development Status :: 5 - Production/Stable
Classifier: Programming Language :: Python
Classifier: Programming Language :: Python :: 3.8
Classifier: Programming Language :: Python :: 3.9
Classifier: Programming Language :: Python :: 3.10
Classifier: Programming Language :: Python :: 3.11
Classifier: Programming Language :: Python :: 3.12
Classifier: Programming Language :: Python :: Implementation :: CPython
Classifier: Programming Language :: Python :: Implementation :: PyPy
Classifier: Operating System :: OS Independent
Classifier: License :: OSI Approved :: MIT License
Classifier: Topic :: Software Development :: Libraries
Requires-Python: !=2.7.*,!=3.0.*,!=3.1.*,!=3.2.*,!=3.3.*,!=3.4.*,!=3.5.*,!=3.6.*,!=3.7.*
License-File: LICENSE
